nonebot_plugin_majsoul/__init__.py
nonebot_plugin_majsoul/ac.py
nonebot_plugin_majsoul/binding/__init__.py
nonebot_plugin_majsoul/config.py
nonebot_plugin_majsoul/data/__init__.py
nonebot_plugin_majsoul/data/account_binding.py
nonebot_plugin_majsoul/data/migrations/a3865d6ed01e_init_db.py
nonebot_plugin_majsoul/errors.py
nonebot_plugin_majsoul/network/__init__.py
nonebot_plugin_majsoul/network/auto_retry.py
nonebot_plugin_majsoul/network/host_prober.py
nonebot_plugin_majsoul/paifuya/__init__.py
nonebot_plugin_majsoul/paifuya/data/__init__.py
nonebot_plugin_majsoul/paifuya/data/api.py
nonebot_plugin_majsoul/paifuya/data/models/__init__.py
nonebot_plugin_majsoul/paifuya/data/models/game_record.py
nonebot_plugin_majsoul/paifuya/data/models/player_extended_stats.py
nonebot_plugin_majsoul/paifuya/data/models/player_info.py
nonebot_plugin_majsoul/paifuya/data/models/player_num.py
nonebot_plugin_majsoul/paifuya/data/models/player_rank.py
nonebot_plugin_majsoul/paifuya/data/models/player_stats.py
nonebot_plugin_majsoul/paifuya/data/models/room_rank.py
nonebot_plugin_majsoul/paifuya/mappers/__init__.py
nonebot_plugin_majsoul/paifuya/mappers/game_record.py
nonebot_plugin_majsoul/paifuya/mappers/general.py
nonebot_plugin_majsoul/paifuya/mappers/player_extended_stats.py
nonebot_plugin_majsoul/paifuya/mappers/player_num.py
nonebot_plugin_majsoul/paifuya/mappers/player_rank.py
nonebot_plugin_majsoul/paifuya/mappers/player_stats.py
nonebot_plugin_majsoul/paifuya/mappers/room_rank.py
nonebot_plugin_majsoul/paifuya/parsers/__init__.py
nonebot_plugin_majsoul/paifuya/parsers/limit_of_games.py
nonebot_plugin_majsoul/paifuya/parsers/name.py
nonebot_plugin_majsoul/paifuya/parsers/room_rank.py
nonebot_plugin_majsoul/paifuya/parsers/time_span.py
nonebot_plugin_majsoul/paifuya/query_majsoul_info.py
nonebot_plugin_majsoul/paifuya/query_majsoul_pt_plot.py
nonebot_plugin_majsoul/paifuya/query_majsoul_records.py
nonebot_plugin_majsoul/paipu/__init__.py
nonebot_plugin_majsoul-0.2.10.dist-info/LICENSE
nonebot_plugin_majsoul-0.2.10.dist-info/METADATA
nonebot_plugin_majsoul-0.2.10.dist-info/WHEEL
nonebot_plugin_majsoul-0.2.10.dist-info/RECORD
