Metadata-Version: 2.3
Name: nonebot-plugin-majsoul
Version: 0.2.10
Summary: NoneBot2 雀魂信息查询插件
License: AGPL-3.0
Author: ssttkkl
Author-email: huang.wen.long@hotmail.com
Requires-Python: >=3.9,<4.0
Classifier: License :: OSI Approved :: GNU Affero General Public License v3
Classifier: Programming Language :: Python :: 3
Classifier: Programming Language :: Python :: 3.9
Classifier: Programming Language :: Python :: 3.10
Classifier: Programming Language :: Python :: 3.11
Classifier: Programming Language :: Python :: 3.12
Classifier: Programming Language :: Python :: 3.13
Requires-Dist: icmplib (>=3.0.3)
Requires-Dist: matplotlib (>=3.6.2)
Requires-Dist: monthdelta (>=0.9.1)
Requires-Dist: nonebot-plugin-access-control-api (>=1.2.1,<2.0.0)
Requires-Dist: nonebot-plugin-orm (>=0.7.0,<1.0.0)
Requires-Dist: nonebot-plugin-send-anything-anywhere (>=0.2.1)
Requires-Dist: nonebot-plugin-user (>=0.4.3,<0.5.0)
Requires-Dist: nonebot2[httpx] (>=2.0.0)
Requires-Dist: ssttkkl-nonebot-utils (>=0.1.23)
Requires-Dist: tensoul (>=0.1.0)
Requires-Dist: tzlocal (>=4.2)
